[
  {
    "id": 1,
    "no_surat": 1,
    "nama_surat": "Al-Fatihah",
    "turun_di": "Makkiyah",
    "arti_surat": "Pembukaan",
    "createdAt": "2023-11-12 00:00:00",
    "updatedAt": "2023-11-12 00:00:00"
  },
  {
    "id": 2,
    "no_surat": 2,
    "nama_surat": "Al-Baqarah",
    "turun_di": "Madaniyah",
    "arti_surat": "Sapi Betina",
    "createdAt": "2023-11-12 00:00:00",
    "updatedAt": "2023-11-12 00:00:00"
  },
  {
    "id": 3,
    "no_surat": 3,
    "nama_surat": "Ali-Imran",
    "turun_di": "Madaniyah",
    "arti_surat": "Keluarga Imran",
    "createdAt": "2023-11-12 00:00:00",
    "updatedAt": "2023-11-12 00:00:00"
  },
  {
    "id": 4,
    "no_surat": 4,
    "nama_surat": "An-nisa",
    "turun_di": "Madaniyah",
    "arti_surat": "Wanita",
    "createdAt": "2023-11-12 00:00:00",
    "updatedAt": "2023-11-12 00:00:00"
  },
  {
    "id": 5,
    "no_surat": 5,
    "nama_surat": "Al-maidah",
    "turun_di": "Madaniyah",
    "arti_surat": "Hidangan",
    "createdAt": "2023-11-12 00:00:00",
    "updatedAt": "2023-11-12 00:00:00"
  },
  {
    "id": 6,
    "no_surat": 6,
    "nama_surat": "Al-an’am",
    "turun_di": "Makkiyah",
    "arti_surat": "Binatang Ternak",
    "createdAt": "2023-11-12 00:00:00",
    "updatedAt": "2023-11-12 00:00:00"
  },
  {
    "id": 7,
    "no_surat": 7,
    "nama_surat": "Al-a’raf",
    "turun_di": "Makkiyah",
    "arti_surat": "Tempat Tertinggi",
    "createdAt": "2023-11-12 00:00:00",
    "updatedAt": "2023-11-12 00:00:00"
  },
  {
    "id": 8,
    "no_surat": 8,
    "nama_surat": "Al-Anfal",
    "turun_di": "Madaniyah",
    "arti_surat": "Rampasan Peraang",
    "createdAt": "2023-11-12 00:00:00",
    "updatedAt": "2023-11-12 00:00:00"
  },
  {
    "id": 9,
    "no_surat": 9,
    "nama_surat": "At-taubah",
    "turun_di": "Madaniyah",
    "arti_surat": "Pengampunan",
    "createdAt": "2023-11-12 00:00:00",
    "updatedAt": "2023-11-12 00:00:00"
  },
  {
    "id": 10,
    "no_surat": 10,
    "nama_surat": "Yunus",
    "turun_di": "Makkiyah",
    "arti_surat": "Yunus",
    "createdAt": "2023-11-12 00:00:00",
    "updatedAt": "2023-11-12 00:00:00"
  },
  {
    "id": 11,
    "no_surat": 11,
    "nama_surat": "Hud",
    "turun_di": "Makkiyah",
    "arti_surat": "Hud",
    "createdAt": "2023-11-12 00:00:00",
    "updatedAt": "2023-11-12 00:00:00"
  },
  {
    "id": 12,
    "no_surat": 12,
    "nama_surat": "Yusuf",
    "turun_di": "Makkiyah",
    "arti_surat": "Yusuf",
    "createdAt": "2023-11-12 00:00:00",
    "updatedAt": "2023-11-12 00:00:00"
  },
  {
    "id": 13,
    "no_surat": 13,
    "nama_surat": "Ar-rad",
    "turun_di": "Madaniyah",
    "arti_surat": "Guruh",
    "createdAt": "2023-11-12 00:00:00",
    "updatedAt": "2023-11-12 00:00:00"
  },
  {
    "id": 14,
    "no_surat": 14,
    "nama_surat": "Ibrahim",
    "turun_di": "Makkiyah",
    "arti_surat": "Ibrahim",
    "createdAt": "2023-11-12 00:00:00",
    "updatedAt": "2023-11-12 00:00:00"
  },
  {
    "id": 15,
    "no_surat": 15,
    "nama_surat": "Al-hijr",
    "turun_di": "Makkiyah",
    "arti_surat": "Negeri Kaum Tsamud",
    "createdAt": "2023-11-12 00:00:00",
    "updatedAt": "2023-11-12 00:00:00"
  },
  {
    "id": 16,
    "no_surat": 16,
    "nama_surat": "An-nahl",
    "turun_di": "Makkiyah",
    "arti_surat": "Lebah",
    "createdAt": "2023-11-12 00:00:00",
    "updatedAt": "2023-11-12 00:00:00"
  },
  {
    "id": 17,
    "no_surat": 17,
    "nama_surat": "Al-isra",
    "turun_di": "Makkiyah",
    "arti_surat": "Perjalanan",
    "createdAt": "2023-11-12 00:00:00",
    "updatedAt": "2023-11-12 00:00:00"
  },
  {
    "id": 18,
    "no_surat": 18,
    "nama_surat": "Al-Kahf",
    "turun_di": "Makkiyah",
    "arti_surat": "Gua",
    "createdAt": "2023-11-12 00:00:00",
    "updatedAt": "2023-11-12 00:00:00"
  },
  {
    "id": 19,
    "no_surat": 19,
    "nama_surat": "Maryam",
    "turun_di": "Makkiyah",
    "arti_surat": "Maryam",
    "createdAt": "2023-11-12 00:00:00",
    "updatedAt": "2023-11-12 00:00:00"
  },
  {
    "id": 20,
    "no_surat": 20,
    "nama_surat": "Thaha",
    "turun_di": "Makkiyah",
    "arti_surat": "Ta ha",
    "createdAt": "2023-11-12 00:00:00",
    "updatedAt": "2023-11-12 00:00:00"
  },
  {
    "id": 21,
    "no_surat": 21,
    "nama_surat": "Al-anbiyaa",
    "turun_di": "Makkiyah",
    "arti_surat": "Nabi-nabi",
    "createdAt": "2023-11-12 00:00:00",
    "updatedAt": "2023-11-12 00:00:00"
  },
  {
    "id": 22,
    "no_surat": 22,
    "nama_surat": "Al-hajj",
    "turun_di": "Madaniyah",
    "arti_surat": "Haji",
    "createdAt": "2023-11-12 00:00:00",
    "updatedAt": "2023-11-12 00:00:00"
  },
  {
    "id": 23,
    "no_surat": 23,
    "nama_surat": "Al-mu’minun",
    "turun_di": "Makkiyah",
    "arti_surat": "Orang-orang yang Beriman",
    "createdAt": "2023-11-12 00:00:00",
    "updatedAt": "2023-11-12 00:00:00"
  },
  {
    "id": 24,
    "no_surat": 24,
    "nama_surat": "An-nur",
    "turun_di": "Madaniyah",
    "arti_surat": "Cahaya",
    "createdAt": "2023-11-12 00:00:00",
    "updatedAt": "2023-11-12 00:00:00"
  },
  {
    "id": 25,
    "no_surat": 25,
    "nama_surat": "Al-furqon",
    "turun_di": "Makkiyah",
    "arti_surat": "Pembeda",
    "createdAt": "2023-11-12 00:00:00",
    "updatedAt": "2023-11-12 00:00:00"
  },
  {
    "id": 26,
    "no_surat": 26,
    "nama_surat": "Asy-syu’ara",
    "turun_di": "Makkiyah",
    "arti_surat": "Para Penyair",
    "createdAt": "2023-11-12 00:00:00",
    "updatedAt": "2023-11-12 00:00:00"
  },
  {
    "id": 27,
    "no_surat": 27,
    "nama_surat": "An-Naml",
    "turun_di": "Makkiyah",
    "arti_surat": "Semut",
    "createdAt": "2023-11-12 00:00:00",
    "updatedAt": "2023-11-12 00:00:00"
  },
  {
    "id": 28,
    "no_surat": 28,
    "nama_surat": "Al-qasas",
    "turun_di": "Makkiyah",
    "arti_surat": "Cerita-Cerita",
    "createdAt": "2023-11-12 00:00:00",
    "updatedAt": "2023-11-12 00:00:00"
  },
  {
    "id": 29,
    "no_surat": 29,
    "nama_surat": "Al-‘ankabut",
    "turun_di": "Makkiyah",
    "arti_surat": "Laba-laba",
    "createdAt": "2023-11-12 00:00:00",
    "updatedAt": "2023-11-12 00:00:00"
  },
  {
    "id": 30,
    "no_surat": 30,
    "nama_surat": "Ar-rum",
    "turun_di": "Makkiyah",
    "arti_surat": "Kaum Romawi",
    "createdAt": "2023-11-12 00:00:00",
    "updatedAt": "2023-11-12 00:00:00"
  },
  {
    "id": 31,
    "no_surat": 31,
    "nama_surat": "Luqman",
    "turun_di": "Makkiyah",
    "arti_surat": "Luqman",
    "createdAt": "2023-11-12 00:00:00",
    "updatedAt": "2023-11-12 00:00:00"
  },
  {
    "id": 32,
    "no_surat": 32,
    "nama_surat": "As-sajdah",
    "turun_di": "Makkiyah",
    "arti_surat": "Sujud",
    "createdAt": "2023-11-12 00:00:00",
    "updatedAt": "2023-11-12 00:00:00"
  },
  {
    "id": 33,
    "no_surat": 33,
    "nama_surat": "Al-Ahzab",
    "turun_di": "Madaniyah",
    "arti_surat": "Golongan yang Bersekutu",
    "createdAt": "2023-11-12 00:00:00",
    "updatedAt": "2023-11-12 00:00:00"
  },
  {
    "id": 34,
    "no_surat": 34,
    "nama_surat": "Saba",
    "turun_di": "Makkiyah",
    "arti_surat": "Kaum Saba’",
    "createdAt": "2023-11-12 00:00:00",
    "updatedAt": "2023-11-12 00:00:00"
  },
  {
    "id": 35,
    "no_surat": 35,
    "nama_surat": "Fatir",
    "turun_di": "Makkiyah",
    "arti_surat": "Pencipta",
    "createdAt": "2023-11-12 00:00:00",
    "updatedAt": "2023-11-12 00:00:00"
  },
  {
    "id": 36,
    "no_surat": 36,
    "nama_surat": "Yasin",
    "turun_di": "Makkiyah",
    "arti_surat": "Ya Sin",
    "createdAt": "2023-11-12 00:00:00",
    "updatedAt": "2023-11-12 00:00:00"
  },
  {
    "id": 37,
    "no_surat": 37,
    "nama_surat": "As-Saffat",
    "turun_di": "Makkiyah",
    "arti_surat": "Yang Bersaf-saf",
    "createdAt": "2023-11-12 00:00:00",
    "updatedAt": "2023-11-12 00:00:00"
  },
  {
    "id": 38,
    "no_surat": 38,
    "nama_surat": "Sad",
    "turun_di": "Makkiyah",
    "arti_surat": "Sad",
    "createdAt": "2023-11-12 00:00:00",
    "updatedAt": "2023-11-12 00:00:00"
  },
  {
    "id": 39,
    "no_surat": 39,
    "nama_surat": "Az-zumar",
    "turun_di": "Makkiyah",
    "arti_surat": "Rombongan-rombongan",
    "createdAt": "2023-11-12 00:00:00",
    "updatedAt": "2023-11-12 00:00:00"
  },
  {
    "id": 40,
    "no_surat": 40,
    "nama_surat": "Al-mu’min",
    "turun_di": "Makkiyah",
    "arti_surat": "Orang Beriman",
    "createdAt": "2023-11-12 00:00:00",
    "updatedAt": "2023-11-12 00:00:00"
  },
  {
    "id": 41,
    "no_surat": 41,
    "nama_surat": "Fussilat",
    "turun_di": "Makkiyah",
    "arti_surat": "Ha Mim",
    "createdAt": "2023-11-12 00:00:00",
    "updatedAt": "2023-11-12 00:00:00"
  },
  {
    "id": 42,
    "no_surat": 42,
    "nama_surat": "Asy-syura",
    "turun_di": "Makkiyah",
    "arti_surat": "Musyawarah",
    "createdAt": "2023-11-12 00:00:00",
    "updatedAt": "2023-11-12 00:00:00"
  },
  {
    "id": 43,
    "no_surat": 43,
    "nama_surat": "Az-zukhruf",
    "turun_di": "Makkiyah",
    "arti_surat": "Perhiasan",
    "createdAt": "2023-11-12 00:00:00",
    "updatedAt": "2023-11-12 00:00:00"
  },
  {
    "id": 44,
    "no_surat": 44,
    "nama_surat": "Ad-dukhan",
    "turun_di": "Makkiyah",
    "arti_surat": "Kabut",
    "createdAt": "2023-11-12 00:00:00",
    "updatedAt": "2023-11-12 00:00:00"
  },
  {
    "id": 45,
    "no_surat": 45,
    "nama_surat": "Al-Jasiyah",
    "turun_di": "Makkiyah",
    "arti_surat": "Yang Berlutut",
    "createdAt": "2023-11-12 00:00:00",
    "updatedAt": "2023-11-12 00:00:00"
  },
  {
    "id": 46,
    "no_surat": 46,
    "nama_surat": "Al-ahqaf",
    "turun_di": "Makkiyah",
    "arti_surat": "Bukit-Bukit Pasir",
    "createdAt": "2023-11-12 00:00:00",
    "updatedAt": "2023-11-12 00:00:00"
  },
  {
    "id": 47,
    "no_surat": 47,
    "nama_surat": "Muhammad",
    "turun_di": "Madaniyah",
    "arti_surat": "Nabi Muhammad SAW",
    "createdAt": "2023-11-12 00:00:00",
    "updatedAt": "2023-11-12 00:00:00"
  },
  {
    "id": 48,
    "no_surat": 48,
    "nama_surat": "Al-fath",
    "turun_di": "Madaniyah",
    "arti_surat": "Kemenangan",
    "createdAt": "2023-11-12 00:00:00",
    "updatedAt": "2023-11-12 00:00:00"
  },
  {
    "id": 49,
    "no_surat": 49,
    "nama_surat": "Al-hujaraat",
    "turun_di": "Madaniyah",
    "arti_surat": "Kamar-Kamar",
    "createdAt": "2023-11-12 00:00:00",
    "updatedAt": "2023-11-12 00:00:00"
  },
  {
    "id": 50,
    "no_surat": 50,
    "nama_surat": "Qaf",
    "turun_di": "Makkiyah",
    "arti_surat": "Qaf",
    "createdAt": "2023-11-12 00:00:00",
    "updatedAt": "2023-11-12 00:00:00"
  },
  {
    "id": 51,
    "no_surat": 51,
    "nama_surat": "Az-Zariyat",
    "turun_di": "Makkiyah",
    "arti_surat": "Angin Yang Menerbangkan",
    "createdAt": "2023-11-12 00:00:00",
    "updatedAt": "2023-11-12 00:00:00"
  },
  {
    "id": 52,
    "no_surat": 52,
    "nama_surat": "At-tur",
    "turun_di": "Makkiyah",
    "arti_surat": "bukit",
    "createdAt": "2023-11-12 00:00:00",
    "updatedAt": "2023-11-12 00:00:00"
  },
  {
    "id": 53,
    "no_surat": 53,
    "nama_surat": "An-najm",
    "turun_di": "Makkiyah",
    "arti_surat": "Bintang",
    "createdAt": "2023-11-12 00:00:00",
    "updatedAt": "2023-11-12 00:00:00"
  },
  {
    "id": 54,
    "no_surat": 54,
    "nama_surat": "Al-qamar",
    "turun_di": "Makkiyah",
    "arti_surat": "Bulan",
    "createdAt": "2023-11-12 00:00:00",
    "updatedAt": "2023-11-12 00:00:00"
  },
  {
    "id": 55,
    "no_surat": 55,
    "nama_surat": "Ar-rahman",
    "turun_di": "Madaniyah",
    "arti_surat": "Yang Maha Pemurah",
    "createdAt": "2023-11-12 00:00:00",
    "updatedAt": "2023-11-12 00:00:00"
  },
  {
    "id": 56,
    "no_surat": 56,
    "nama_surat": "Al-waqi’ah",
    "turun_di": "Makkiyah",
    "arti_surat": "Hari Kiamat",
    "createdAt": "2023-11-12 00:00:00",
    "updatedAt": "2023-11-12 00:00:00"
  },
  {
    "id": 57,
    "no_surat": 57,
    "nama_surat": "Al-hadid",
    "turun_di": "Madaniyah",
    "arti_surat": "Besi",
    "createdAt": "2023-11-12 00:00:00",
    "updatedAt": "2023-11-12 00:00:00"
  },
  {
    "id": 58,
    "no_surat": 58,
    "nama_surat": "Al-mujadilah",
    "turun_di": "Madaniyah",
    "arti_surat": "Wanita yang Mengajukan Gugatan",
    "createdAt": "2023-11-12 00:00:00",
    "updatedAt": "2023-11-12 00:00:00"
  },
  {
    "id": 59,
    "no_surat": 59,
    "nama_surat": "Al-hasyr",
    "turun_di": "Madaniyah",
    "arti_surat": "Pengusiran",
    "createdAt": "2023-11-12 00:00:00",
    "updatedAt": "2023-11-12 00:00:00"
  },
  {
    "id": 60,
    "no_surat": 60,
    "nama_surat": "Al-mumtahanah",
    "turun_di": "Madaniyah",
    "arti_surat": "Perempuan yang Diuji",
    "createdAt": "2023-11-12 00:00:00",
    "updatedAt": "2023-11-12 00:00:00"
  },
  {
    "id": 61,
    "no_surat": 61,
    "nama_surat": "As-shaff",
    "turun_di": "Madaniyah",
    "arti_surat": "Barisan",
    "createdAt": "2023-11-12 00:00:00",
    "updatedAt": "2023-11-12 00:00:00"
  },
  {
    "id": 62,
    "no_surat": 62,
    "nama_surat": "Al-jumu’ah",
    "turun_di": "Madaniyah",
    "arti_surat": "Hari Jum’at",
    "createdAt": "2023-11-12 00:00:00",
    "updatedAt": "2023-11-12 00:00:00"
  },
  {
    "id": 63,
    "no_surat": 63,
    "nama_surat": "Al-munafiqun",
    "turun_di": "Madaniyah",
    "arti_surat": "Orang-Orang Munafiq",
    "createdAt": "2023-11-12 00:00:00",
    "updatedAt": "2023-11-12 00:00:00"
  },
  {
    "id": 64,
    "no_surat": 64,
    "nama_surat": "At-taghabun",
    "turun_di": "Madaniyah",
    "arti_surat": "Hari Ditampakkan Segala Kesalahan",
    "createdAt": "2023-11-12 00:00:00",
    "updatedAt": "2023-11-12 00:00:00"
  },
  {
    "id": 65,
    "no_surat": 65,
    "nama_surat": "At-talaq",
    "turun_di": "Madaniyah",
    "arti_surat": "Talak",
    "createdAt": "2023-11-12 00:00:00",
    "updatedAt": "2023-11-12 00:00:00"
  },
  {
    "id": 66,
    "no_surat": 66,
    "nama_surat": "At-tahrim",
    "turun_di": "Madaniyah",
    "arti_surat": "Mengharamkan",
    "createdAt": "2023-11-12 00:00:00",
    "updatedAt": "2023-11-12 00:00:00"
  },
  {
    "id": 67,
    "no_surat": 67,
    "nama_surat": "Al-mulk",
    "turun_di": "Makkiyah",
    "arti_surat": "Kerajaan",
    "createdAt": "2023-11-12 00:00:00",
    "updatedAt": "2023-11-12 00:00:00"
  },
  {
    "id": 68,
    "no_surat": 68,
    "nama_surat": "Al-qalam",
    "turun_di": "Makkiyah",
    "arti_surat": "Kalam",
    "createdAt": "2023-11-12 00:00:00",
    "updatedAt": "2023-11-12 00:00:00"
  },
  {
    "id": 69,
    "no_surat": 69,
    "nama_surat": "Al-haqqah",
    "turun_di": "Makkiyah",
    "arti_surat": "Hari Kiamat",
    "createdAt": "2023-11-12 00:00:00",
    "updatedAt": "2023-11-12 00:00:00"
  },
  {
    "id": 70,
    "no_surat": 70,
    "nama_surat": "Al-ma’arij",
    "turun_di": "Makkiyah",
    "arti_surat": "Tempat-tempat Naik",
    "createdAt": "2023-11-12 00:00:00",
    "updatedAt": "2023-11-12 00:00:00"
  },
  {
    "id": 71,
    "no_surat": 71,
    "nama_surat": "Nuh",
    "turun_di": "Makkiyah",
    "arti_surat": "Nuh",
    "createdAt": "2023-11-12 00:00:00",
    "updatedAt": "2023-11-12 00:00:00"
  },
  {
    "id": 72,
    "no_surat": 72,
    "nama_surat": "Al-jin",
    "turun_di": "Makkiyah",
    "arti_surat": "Jin",
    "createdAt": "2023-11-12 00:00:00",
    "updatedAt": "2023-11-12 00:00:00"
  },
  {
    "id": 73,
    "no_surat": 73,
    "nama_surat": "Al-muzammil",
    "turun_di": "Makkiyah",
    "arti_surat": "Orang yang Berselimut",
    "createdAt": "2023-11-12 00:00:00",
    "updatedAt": "2023-11-12 00:00:00"
  },
  {
    "id": 74,
    "no_surat": 74,
    "nama_surat": "Al-muddassir",
    "turun_di": "Makkiyah",
    "arti_surat": "Orang Yang Berkemul",
    "createdAt": "2023-11-12 00:00:00",
    "updatedAt": "2023-11-12 00:00:00"
  },
  {
    "id": 75,
    "no_surat": 75,
    "nama_surat": "Al-qiyamah",
    "turun_di": "Makkiyah",
    "arti_surat": "Hari Kiamat",
    "createdAt": "2023-11-12 00:00:00",
    "updatedAt": "2023-11-12 00:00:00"
  },
  {
    "id": 76,
    "no_surat": 76,
    "nama_surat": "Al-insan",
    "turun_di": "Madaniyah",
    "arti_surat": "Al Insan",
    "createdAt": "2023-11-12 00:00:00",
    "updatedAt": "2023-11-12 00:00:00"
  },
  {
    "id": 77,
    "no_surat": 77,
    "nama_surat": "Al-mursalat",
    "turun_di": "Makkiyah",
    "arti_surat": "Malaikat-malaikat yang Diutus",
    "createdAt": "2023-11-12 00:00:00",
    "updatedAt": "2023-11-12 00:00:00"
  },
  {
    "id": 78,
    "no_surat": 78,
    "nama_surat": "An-naba",
    "turun_di": "Makkiyah",
    "arti_surat": "Berita Besar",
    "createdAt": "2023-11-12 00:00:00",
    "updatedAt": "2023-11-12 00:00:00"
  },
  {
    "id": 79,
    "no_surat": 79,
    "nama_surat": "An-nazi’at",
    "turun_di": "Makkiyah",
    "arti_surat": "Malaikat-malaikat yang Mencabut",
    "createdAt": "2023-11-12 00:00:00",
    "updatedAt": "2023-11-12 00:00:00"
  },
  {
    "id": 80,
    "no_surat": 80,
    "nama_surat": "Abasa",
    "turun_di": "Makkiyah",
    "arti_surat": "Ia Bermuka Masam",
    "createdAt": "2023-11-12 00:00:00",
    "updatedAt": "2023-11-12 00:00:00"
  },
  {
    "id": 81,
    "no_surat": 81,
    "nama_surat": "At-takwir",
    "turun_di": "Makkiyah",
    "arti_surat": "Menggulung",
    "createdAt": "2023-11-12 00:00:00",
    "updatedAt": "2023-11-12 00:00:00"
  },
  {
    "id": 82,
    "no_surat": 82,
    "nama_surat": "Al-infitar",
    "turun_di": "Makkiyah",
    "arti_surat": "Terbelah",
    "createdAt": "2023-11-12 00:00:00",
    "updatedAt": "2023-11-12 00:00:00"
  },
  {
    "id": 83,
    "no_surat": 83,
    "nama_surat": "Al-mutaffifin",
    "turun_di": "Makkiyah",
    "arti_surat": "Kecurangan",
    "createdAt": "2023-11-12 00:00:00",
    "updatedAt": "2023-11-12 00:00:00"
  },
  {
    "id": 84,
    "no_surat": 84,
    "nama_surat": "Al-Insyiqaq",
    "turun_di": "Makkiyah",
    "arti_surat": "Terbelah",
    "createdAt": "2023-11-12 00:00:00",
    "updatedAt": "2023-11-12 00:00:00"
  },
  {
    "id": 85,
    "no_surat": 85,
    "nama_surat": "Al-buruj",
    "turun_di": "Makkiyah",
    "arti_surat": "Gugusan Bintang",
    "createdAt": "2023-11-12 00:00:00",
    "updatedAt": "2023-11-12 00:00:00"
  },
  {
    "id": 86,
    "no_surat": 86,
    "nama_surat": "At-tariq",
    "turun_di": "Makkiyah",
    "arti_surat": "Yang Datang di Malam Hari",
    "createdAt": "2023-11-12 00:00:00",
    "updatedAt": "2023-11-12 00:00:00"
  },
  {
    "id": 87,
    "no_surat": 87,
    "nama_surat": "Al-a’la",
    "turun_di": "Makkiyah",
    "arti_surat": "Yang Paling Tinggi",
    "createdAt": "2023-11-12 00:00:00",
    "updatedAt": "2023-11-12 00:00:00"
  },
  {
    "id": 88,
    "no_surat": 88,
    "nama_surat": "Al-ghasyiyah",
    "turun_di": "Makkiyah",
    "arti_surat": "Hari Pembalasan",
    "createdAt": "2023-11-12 00:00:00",
    "updatedAt": "2023-11-12 00:00:00"
  },
  {
    "id": 89,
    "no_surat": 89,
    "nama_surat": "Al-fajr",
    "turun_di": "Makkiyah",
    "arti_surat": "Fajar",
    "createdAt": "2023-11-12 00:00:00",
    "updatedAt": "2023-11-12 00:00:00"
  },
  {
    "id": 90,
    "no_surat": 90,
    "nama_surat": "Al-balad",
    "turun_di": "Makkiyah",
    "arti_surat": "Negeri",
    "createdAt": "2023-11-12 00:00:00",
    "updatedAt": "2023-11-12 00:00:00"
  },
  {
    "id": 91,
    "no_surat": 91,
    "nama_surat": "Asy-syams",
    "turun_di": "Makkiyah",
    "arti_surat": "Matahari",
    "createdAt": "2023-11-12 00:00:00",
    "updatedAt": "2023-11-12 00:00:00"
  },
  {
    "id": 92,
    "no_surat": 92,
    "nama_surat": "Al-lail",
    "turun_di": "Makkiyah",
    "arti_surat": "Malam",
    "createdAt": "2023-11-12 00:00:00",
    "updatedAt": "2023-11-12 00:00:00"
  },
  {
    "id": 93,
    "no_surat": 93,
    "nama_surat": "Ad-dhuha",
    "turun_di": "Makkiyah",
    "arti_surat": "Waktu Dhuha",
    "createdAt": "2023-11-12 00:00:00",
    "updatedAt": "2023-11-12 00:00:00"
  },
  {
    "id": 94,
    "no_surat": 94,
    "nama_surat": "Al-insyirah",
    "turun_di": "Makkiyah",
    "arti_surat": "Kelapangan",
    "createdAt": "2023-11-12 00:00:00",
    "updatedAt": "2023-11-12 00:00:00"
  },
  {
    "id": 95,
    "no_surat": 95,
    "nama_surat": "At-tin",
    "turun_di": "Makkiyah",
    "arti_surat": "Buah Tin",
    "createdAt": "2023-11-12 00:00:00",
    "updatedAt": "2023-11-12 00:00:00"
  },
  {
    "id": 96,
    "no_surat": 96,
    "nama_surat": "Al-alaq",
    "turun_di": "Makkiyah",
    "arti_surat": "Segumpal Darah",
    "createdAt": "2023-11-12 00:00:00",
    "updatedAt": "2023-11-12 00:00:00"
  },
  {
    "id": 97,
    "no_surat": 97,
    "nama_surat": "Al-qadr",
    "turun_di": "Makkiyah",
    "arti_surat": "Kemuliaan",
    "createdAt": "2023-11-12 00:00:00",
    "updatedAt": "2023-11-12 00:00:00"
  },
  {
    "id": 98,
    "no_surat": 98,
    "nama_surat": "Al-bayyinah",
    "turun_di": "Madaniyah",
    "arti_surat": "Bukti yang Nyata",
    "createdAt": "2023-11-12 00:00:00",
    "updatedAt": "2023-11-12 00:00:00"
  },
  {
    "id": 99,
    "no_surat": 99,
    "nama_surat": "Al-zalzalah",
    "turun_di": "Madaniyah",
    "arti_surat": "Keguncangan",
    "createdAt": "2023-11-12 00:00:00",
    "updatedAt": "2023-11-12 00:00:00"
  },
  {
    "id": 100,
    "no_surat": 100,
    "nama_surat": "Al-adiyat",
    "turun_di": "Makkiyah",
    "arti_surat": "Kuda Perang yang Berlari Kencang",
    "createdAt": "2023-11-12 00:00:00",
    "updatedAt": "2023-11-12 00:00:00"
  },
  {
    "id": 101,
    "no_surat": 101,
    "nama_surat": "Al-qoriah",
    "turun_di": "Makkiyah",
    "arti_surat": "Hari Kiamat",
    "createdAt": "2023-11-12 00:00:00",
    "updatedAt": "2023-11-12 00:00:00"
  },
  {
    "id": 102,
    "no_surat": 102,
    "nama_surat": "At-takatsur",
    "turun_di": "Makkiyah",
    "arti_surat": "Bermegah-Megahan",
    "createdAt": "2023-11-12 00:00:00",
    "updatedAt": "2023-11-12 00:00:00"
  },
  {
    "id": 103,
    "no_surat": 103,
    "nama_surat": "Al-ashr",
    "turun_di": "Makkiyah",
    "arti_surat": "Masa",
    "createdAt": "2023-11-12 00:00:00",
    "updatedAt": "2023-11-12 00:00:00"
  },
  {
    "id": 104,
    "no_surat": 104,
    "nama_surat": "Al-humazah",
    "turun_di": "Makkiyah",
    "arti_surat": "Pengumpat",
    "createdAt": "2023-11-12 00:00:00",
    "updatedAt": "2023-11-12 00:00:00"
  },
  {
    "id": 105,
    "no_surat": 105,
    "nama_surat": "Al-fil",
    "turun_di": "Makkiyah",
    "arti_surat": "Gajah",
    "createdAt": "2023-11-12 00:00:00",
    "updatedAt": "2023-11-12 00:00:00"
  },
  {
    "id": 106,
    "no_surat": 106,
    "nama_surat": "Al-quraisy",
    "turun_di": "Makkiyah",
    "arti_surat": "Suku Quraysy",
    "createdAt": "2023-11-12 00:00:00",
    "updatedAt": "2023-11-12 00:00:00"
  },
  {
    "id": 107,
    "no_surat": 107,
    "nama_surat": "Al-maun",
    "turun_di": "Makkiyah",
    "arti_surat": "Barang-Barang Yang Berguna",
    "createdAt": "2023-11-12 00:00:00",
    "updatedAt": "2023-11-12 00:00:00"
  },
  {
    "id": 108,
    "no_surat": 108,
    "nama_surat": "Al-kautsar",
    "turun_di": "Makkiyah",
    "arti_surat": "Nikmat Yang Banyak",
    "createdAt": "2023-11-12 00:00:00",
    "updatedAt": "2023-11-12 00:00:00"
  },
  {
    "id": 109,
    "no_surat": 109,
    "nama_surat": "Al-kafirun",
    "turun_di": "Makkiyah",
    "arti_surat": "Orang-orang Kafir",
    "createdAt": "2023-11-12 00:00:00",
    "updatedAt": "2023-11-12 00:00:00"
  },
  {
    "id": 110,
    "no_surat": 110,
    "nama_surat": "An-nasr",
    "turun_di": "Madaniyah",
    "arti_surat": "Pertolongan",
    "createdAt": "2023-11-12 00:00:00",
    "updatedAt": "2023-11-12 00:00:00"
  },
  {
    "id": 111,
    "no_surat": 111,
    "nama_surat": "Al-lahab",
    "turun_di": "Makkiyah",
    "arti_surat": "Gejolak Api",
    "createdAt": "2023-11-12 00:00:00",
    "updatedAt": "2023-11-12 00:00:00"
  },
  {
    "id": 112,
    "no_surat": 112,
    "nama_surat": "Al-ikhlas",
    "turun_di": "Makkiyah",
    "arti_surat": "Memurnikan Keesaan Allah",
    "createdAt": "2023-11-12 00:00:00",
    "updatedAt": "2023-11-12 00:00:00"
  },
  {
    "id": 113,
    "no_surat": 113,
    "nama_surat": "Al-falaq",
    "turun_di": "Makkiyah",
    "arti_surat": "Waktu Subuh",
    "createdAt": "2023-11-12 00:00:00",
    "updatedAt": "2023-11-12 00:00:00"
  },
  {
    "id": 114,
    "no_surat": 114,
    "nama_surat": "an-naas",
    "turun_di": "Makkiyah",
    "arti_surat": "Manusia",
    "createdAt": "2023-11-12 00:00:00",
    "updatedAt": "2023-11-12 00:00:00"
  }
]
